pg_metadata_mcp_server/__init__.py
pg_metadata_mcp_server/server.py
pg_metadata_mcp_server-0.11.0.dist-info/METADATA
pg_metadata_mcp_server-0.11.0.dist-info/WHEEL
pg_metadata_mcp_server-0.11.0.dist-info/entry_points.txt
pg_metadata_mcp_server-0.11.0.dist-info/RECORD
