Metadata-Version: 2.4
Name: pg-metadata-mcp-server
Version: 0.11.0
Summary: Add your description here
Author-email: lishuang <lishuang@microconnect.com>
Requires-Python: >=3.10
Requires-Dist: bs4>=0.0.2
Requires-Dist: dashscope>=1.23.8
Requires-Dist: dotenv>=0.9.9
Requires-Dist: httpx>=0.28.1
Requires-Dist: mcp[cli]>=1.11.0
Requires-Dist: psycopg2>=2.9.10
Requires-Dist: requests>=2.32.4
